lightifypy/Capability.py
lightifypy/Command.py
lightifypy/Constant.py
lightifypy/DeviceType.py
lightifypy/Errors.py
lightifypy/LightifyLight.py
lightifypy/LightifyLink.py
lightifypy/LightifyLuminary.py
lightifypy/LightifyZone.py
lightifypy/PacketBuilder.py
lightifypy/__init__.py
lightifypy-0.0.6.dist-info/DESCRIPTION.rst
lightifypy-0.0.6.dist-info/METADATA
lightifypy-0.0.6.dist-info/RECORD
lightifypy-0.0.6.dist-info/WHEEL
lightifypy-0.0.6.dist-info/metadata.json
lightifypy-0.0.6.dist-info/top_level.txt
