Metadata-Version: 2.0
Name: lightifypy
Version: 0.0.6
Summary: A library to work with OSRAM lightify.
Home-page: https://github.com/zabuldon/Lightifypy
Author: Sergey Isachenko
Author-email: sergey.isachenkol@bool.by
License: WTFPL
Platform: UNKNOWN
Classifier: Intended Audience :: Developers
Classifier: Operating System :: OS Independent
Classifier: Programming Language :: Python :: 3
Classifier: Programming Language :: Python :: 3.4
Classifier: Programming Language :: Python :: 3.5
Classifier: Topic :: Internet
